pylabel/__init__.py
pylabel/analyze.py
pylabel/dataset.py
pylabel/exporter.py
pylabel/importer.py
pylabel/labeler.py
pylabel/shared.py
pylabel/splitter.py
pylabel/visualize.py
pylabel-0.1.55.dist-info/LICENSE.txt
pylabel-0.1.55.dist-info/METADATA
pylabel-0.1.55.dist-info/WHEEL
pylabel-0.1.55.dist-info/top_level.txt
pylabel-0.1.55.dist-info/RECORD
