Metadata-Version: 2.1
Name: pylabel
Version: 0.1.55
Summary: Transform, analyze, and visualize computer vision annotations.
Home-page: https://github.com/pylabel-project/pylabel
Author: PyLabel Project
License: MIT
License-File: LICENSE.txt
Requires-Dist: pandas
Requires-Dist: bbox-visualizer
Requires-Dist: matplotlib
Requires-Dist: opencv-python
Requires-Dist: scikit-learn
Requires-Dist: jupyter-bbox-widget
Requires-Dist: pyyaml
Requires-Dist: tqdm
